odoo/addons/migration_wordpress/__init__.py
odoo/addons/migration_wordpress/__manifest__.py
odoo/addons/migration_wordpress/controllers/__init__.py
odoo/addons/migration_wordpress/controllers/main.py
odoo/addons/migration_wordpress/data/res_groups.xml
odoo/addons/migration_wordpress/models/__init__.py
odoo/addons/migration_wordpress/models/migration_import_wordpress.py
odoo/addons/migration_wordpress/models/website_page.py
odoo/addons/migration_wordpress/security/ir.model.access.csv
odoo/addons/migration_wordpress/static/description/1.jpg
odoo/addons/migration_wordpress/static/description/index.html
odoo/addons/migration_wordpress/views/menus.xml
odoo/addons/migration_wordpress/views/migration_import_wordpress_views.xml
odoo14_addon_migration_wordpress-14.0.2.0.0.dist-info/METADATA
odoo14_addon_migration_wordpress-14.0.2.0.0.dist-info/WHEEL
odoo14_addon_migration_wordpress-14.0.2.0.0.dist-info/top_level.txt
odoo14_addon_migration_wordpress-14.0.2.0.0.dist-info/RECORD
